<?xml version="1.0" encoding="UTF-8"?>
<!DOCTYPE features >

<!-- Maryland State Holidays

     Includes all the federal holidays plus
       Election Day (even years only)
       Day After Thanksgiving
-->

<!-- Holidays for the state of Maryland in The United States -->
<holidayCalendar name="Maryland" type="political">
  <include>UnitedStates/Federal.xml</include>

  <holiday type="public" workDayOff="true" schoolDayOff="true">
    <name>Day After Thanksgiving</name>
    <datespec>
      <posdate position="fourth" dayOfWeek="thursday" month="11">
        <plus days="1"/>
      </posdate>
    </datespec>
    <description>The day after Thanksgiving</description>
  </holiday>

  <holiday type="public" workDayOff="true" schoolDayOff="true">
    <name>Election Day</name>
    <datespec>
      <posdate position="first" dayOfWeek="tuesday" month="11">
        <yearMod>2</yearMod>  <!-- every even year -->
      </posdate>
    </datespec>
    <description>Election Day</description>
  </holiday>

</holidayCalendar>
